LICENSE
README.md
pyproject.toml
setup.py
tyre_energy_label.egg-info/PKG-INFO
tyre_energy_label.egg-info/SOURCES.txt
tyre_energy_label.egg-info/dependency_links.txt
tyre_energy_label.egg-info/entry_points.txt
tyre_energy_label.egg-info/requires.txt
tyre_energy_label.egg-info/top_level.txt
tyre_label/__init__.py
tyre_label/cli.py
tyre_label/label.py
tyre_label/templates/label.svg.j2