Metadata-Version: 2.1
Name: tyre-energy-label
Version: 1.1.0
Summary: EU tyres energy label generator
Home-page: https://github.com/ViktorStiskala/tyre-energy-label
Author: Viktor Stískala
Author-email: viktor@stiskala.cz
License: MIT
Platform: UNKNOWN
Classifier: Intended Audience :: Developers
Classifier: Operating System :: OS Independent
Classifier: Programming Language :: Python
Classifier: Programming Language :: Python :: 3
Classifier: Topic :: Software Development :: Libraries
Classifier: Topic :: Software Development :: Libraries :: Python Modules
